{
  "tasks": [
    {
      "name": "Get 500 from 12399",
      "daytime": "From 8:00 to 18:00 15.07.22",
      "reminder": true,
      "id": 1
    },
    {
      "name": "watch the full course about react 2021",
      "daytime": "",
      "reminder": true,
      "id": 4
    },
    {
      "name": "Still sun from codepen ",
      "daytime": "https://codepen.io/irshadav/pen/GRwKRZ",
      "reminder": false,
      "id": 5
    },
    {
      "name": "Mohit Taks",
      "daytime": "fejdfie",
      "reminder": false,
      "id": 6
    },
    {
      "name": "dekmied",
      "daytime": "iednik",
      "reminder": false,
      "id": 7
    },
    {
      "name": "New Task",
      "daytime": "Frifday",
      "reminder": true,
      "id": 8
    }
  ]
}